MANIFEST.in
README.md
pytest.ini
requirements.txt
setup.cfg
setup.py
tox.ini
examples/.coverage
examples/DebugWindow.py
examples/DebugWindow.pyc
examples/basic.py
examples/cube.py
examples/shaders.py
examples/shaders2.py
examples/uniform.py
oogli/.coverage
oogli/Program.py
oogli/Program.pyc
oogli/Texture.py
oogli/Window.py
oogli/Window.pyc
oogli/__init__.py
oogli/__init__.pyc
oogli/shaders.py
oogli/shaders.pyc
oogli/utils.py
oogli/utils.pyc
oogli.egg-info/PKG-INFO
oogli.egg-info/SOURCES.txt
oogli.egg-info/dependency_links.txt
oogli.egg-info/requires.txt
oogli.egg-info/top_level.txt
oogli/__pycache__/Program.cpython-35.pyc
oogli/__pycache__/Window.cpython-35.pyc
oogli/__pycache__/__init__.cpython-35.pyc
oogli/__pycache__/shaders.cpython-35.pyc