Metadata-Version: 1.1
Name: oogli
Version: 0.1.0
Summary: Oogli is a beautiful object oriented graphics library interface
Home-page: https://github.com/brianbruggeman/oogli.git
Author: Brian Bruggeman
Author-email: brian.m.bruggeman@gmail.com
License: Apache 2.0
Keywords: GLFW,CFFI
Platform: UNKNOWN
Classifier: Topic :: Multimedia :: Graphics
Classifier: Topic :: Multimedia :: Graphics :: 3D Rendering
Classifier: Topic :: Multimedia :: Graphics :: Viewers
Classifier: Topic :: Software Development :: User Interfaces
Classifier: Intended Audience :: Developers
Classifier: Intended Audience :: Education
Classifier: Development Status :: 2 - Pre-Alpha
Classifier: License :: OSI Approved :: Apache Software License
Classifier: License :: Other/Proprietary License
Classifier: Operating System :: OS Independent
Classifier: Programming Language :: Python :: 2.7
Classifier: Programming Language :: Python :: 3.5
Classifier: Programming Language :: Python :: Implementation :: CPython
Classifier: Programming Language :: Python :: Implementation :: PyPy
